pycmdmovie/__init__.py
pycmdmovie/main.py
pycmdmovie/util.py
pycmdmovie-1.1.4.dist-info/LICENSE
pycmdmovie-1.1.4.dist-info/METADATA
pycmdmovie-1.1.4.dist-info/WHEEL
pycmdmovie-1.1.4.dist-info/top_level.txt
pycmdmovie-1.1.4.dist-info/RECORD
