Metadata-Version: 2.1
Name: pycmdmovie
Version: 1.1.4
License-File: LICENSE
Requires-Dist: pillow
Requires-Dist: opencv-python
Requires-Dist: colorama
